lm_cloud_sync/__init__.py
lm_cloud_sync/py.typed
lm_cloud_sync/cli/__init__.py
lm_cloud_sync/cli/aws.py
lm_cloud_sync/cli/azure.py
lm_cloud_sync/cli/gcp.py
lm_cloud_sync/cli/main.py
lm_cloud_sync/core/__init__.py
lm_cloud_sync/core/config.py
lm_cloud_sync/core/exceptions.py
lm_cloud_sync/core/lm_client.py
lm_cloud_sync/core/models.py
lm_cloud_sync/providers/__init__.py
lm_cloud_sync/providers/base.py
lm_cloud_sync/providers/aws/__init__.py
lm_cloud_sync/providers/aws/auth.py
lm_cloud_sync/providers/aws/discovery.py
lm_cloud_sync/providers/aws/groups.py
lm_cloud_sync/providers/aws/provider.py
lm_cloud_sync/providers/azure/__init__.py
lm_cloud_sync/providers/azure/discovery.py
lm_cloud_sync/providers/azure/groups.py
lm_cloud_sync/providers/azure/provider.py
lm_cloud_sync/providers/gcp/__init__.py
lm_cloud_sync/providers/gcp/discovery.py
lm_cloud_sync/providers/gcp/groups.py
lm_cloud_sync/providers/gcp/provider.py
lm_cloud_sync-2.0.7.dist-info/METADATA
lm_cloud_sync-2.0.7.dist-info/WHEEL
lm_cloud_sync-2.0.7.dist-info/entry_points.txt
lm_cloud_sync-2.0.7.dist-info/licenses/LICENSE
lm_cloud_sync-2.0.7.dist-info/RECORD
