Metadata-Version: 2.4
Name: lm-cloud-sync
Version: 2.0.7
Summary: Multi-cloud automation tool for LogicMonitor integrations. GCP and Azure support available, AWS coming soon.
Project-URL: Homepage, https://github.com/ryanmat/lm-cloud-sync
Project-URL: Repository, https://github.com/ryanmat/lm-cloud-sync
Project-URL: Issues, https://github.com/ryanmat/lm-cloud-sync/issues
Author-email: Ryan Matuszewski <rmmatuszewski@gmail.com>
License: MIT
License-File: LICENSE
Keywords: automation,aws,azure,cloud,gcp,logicmonitor,monitoring
Classifier: Development Status :: 4 - Beta
Classifier: Environment :: Console
Classifier: Intended Audience :: System Administrators
Classifier: License :: OSI Approved :: MIT License
Classifier: Operating System :: OS Independent
Classifier: Programming Language :: Python :: 3
Classifier: Programming Language :: Python :: 3.11
Classifier: Programming Language :: Python :: 3.12
Classifier: Topic :: System :: Monitoring
Requires-Python: >=3.11
Requires-Dist: azure-identity>=1.15.0
Requires-Dist: azure-mgmt-subscription>=3.1.0
Requires-Dist: boto3>=1.34.0
Requires-Dist: click>=8.1.0
Requires-Dist: google-auth>=2.20.0
Requires-Dist: google-cloud-resource-manager>=1.10.0
Requires-Dist: httpx>=0.27.0
Requires-Dist: pydantic-settings>=2.0.0
Requires-Dist: pydantic>=2.0.0
Requires-Dist: pyyaml>=6.0
Requires-Dist: rich>=13.0.0
Provides-Extra: dev
Requires-Dist: moto[organizations]>=5.0.0; extra == 'dev'
Requires-Dist: mypy>=1.10.0; extra == 'dev'
Requires-Dist: pytest-cov>=4.0.0; extra == 'dev'
Requires-Dist: pytest-httpx>=0.30.0; extra == 'dev'
Requires-Dist: pytest>=8.0.0; extra == 'dev'
Requires-Dist: ruff>=0.4.0; extra == 'dev'
